{
  "DataModelSettings": {
    "DataStoreFilePath": "{EntryFolder}/DataModel/DataModel.sqlite",
    "IpcDataStoreFilePath": "{EntryFolder}/DataModel/DataModel_IPC.sqlite",
    "ArchiveLocations": [
      "{EntryFolder}/Archives"
    ],
    "MaxHashingJobs": -1,
    "LoadoutDeploymentJobs": -1,
    "MaxHashingThroughputBytesPerSecond": -1
  },
  "FileExtractorSettings": {
    "TempFolderLocation": "{EntryFolder}/Temp"
  },
  "HttpDownloaderSettings": {
    "ChunkCount": 4,
    "WriteQueueLength": 16,
    "MinCancelAge": 500,
    "CancelSpeedFraction": 0.66
  },
  "LoggingSettings": {
    "FilePath": "{EntryFolder}/Logs/nexusmods.app.current.log",
    "ArchiveFilePath": "{EntryFolder}/Logs/nexusmods.app.{##}.log",
    "MaxArchivedFiles": 10
  }
}
